LICENSE
MANIFEST.in
README.rst
setup.py
prospector/__init__.py
prospector/__main__.py
prospector/__pkginfo__.py
prospector/autodetect.py
prospector/blender.py
prospector/blender_combinations.yaml
prospector/encoding.py
prospector/exceptions.py
prospector/finder.py
prospector/message.py
prospector/pathutils.py
prospector/postfilter.py
prospector/run.py
prospector/suppression.py
prospector/config/__init__.py
prospector/config/configuration.py
prospector/formatters/__init__.py
prospector/formatters/base.py
prospector/formatters/emacs.py
prospector/formatters/grouped.py
prospector/formatters/json.py
prospector/formatters/pylint.py
prospector/formatters/text.py
prospector/formatters/vscode.py
prospector/formatters/xunit.py
prospector/formatters/yaml.py
prospector/profiles/__init__.py
prospector/profiles/profile.py
prospector/profiles/profiles/default.yaml
prospector/profiles/profiles/doc_warnings.yaml
prospector/profiles/profiles/flake8.yaml
prospector/profiles/profiles/full_pep8.yaml
prospector/profiles/profiles/member_warnings.yaml
prospector/profiles/profiles/no_doc_warnings.yaml
prospector/profiles/profiles/no_member_warnings.yaml
prospector/profiles/profiles/no_pep8.yaml
prospector/profiles/profiles/no_test_warnings.yaml
prospector/profiles/profiles/strictness_high.yaml
prospector/profiles/profiles/strictness_low.yaml
prospector/profiles/profiles/strictness_medium.yaml
prospector/profiles/profiles/strictness_none.yaml
prospector/profiles/profiles/strictness_veryhigh.yaml
prospector/profiles/profiles/strictness_verylow.yaml
prospector/profiles/profiles/test_warnings.yaml
prospector/tools/__init__.py
prospector/tools/base.py
prospector/tools/utils.py
prospector/tools/dodgy/__init__.py
prospector/tools/frosted/__init__.py
prospector/tools/mccabe/__init__.py
prospector/tools/pep257/__init__.py
prospector/tools/pep8/__init__.py
prospector/tools/profile_validator/__init__.py
prospector/tools/pyflakes/__init__.py
prospector/tools/pylint/__init__.py
prospector_fixes_232.egg-info/PKG-INFO
prospector_fixes_232.egg-info/SOURCES.txt
prospector_fixes_232.egg-info/dependency_links.txt
prospector_fixes_232.egg-info/entry_points.txt
prospector_fixes_232.egg-info/not-zip-safe
prospector_fixes_232.egg-info/requires.txt
prospector_fixes_232.egg-info/top_level.txt