Metadata-Version: 1.1
Name: prospector-fixes-232
Version: 0.12.7
Summary: Prospector: python static analysis tool
Home-page: http://prospector.landscape.io
Author: landscape.io
Author-email: code@landscape.io
License: GPLv2
Keywords: pylint pyflakes pep8 mccabe frosted prospector static code analysis
Platform: UNKNOWN
Classifier: Development Status :: 4 - Beta
Classifier: Environment :: Console
Classifier: Intended Audience :: Developers
Classifier: Operating System :: Unix
Classifier: Topic :: Software Development :: Quality Assurance
Classifier: Programming Language :: Python :: 2.7
Classifier: Programming Language :: Python :: 3.3
Classifier: Programming Language :: Python :: 3.4
Classifier: Programming Language :: Python :: 3.5
Classifier: License :: OSI Approved :: GNU General Public License v2 or later (GPLv2+)
